odoo9_addon_account_check_printing_report_dlt103-9.0.1.0.0-py2.7-nspkg.pth
odoo9_addon_account_check_printing_report_dlt103-9.0.1.0.0.dist-info/top_level.txt
odoo9_addon_account_check_printing_report_dlt103-9.0.1.0.0.dist-info/WHEEL
odoo9_addon_account_check_printing_report_dlt103-9.0.1.0.0.dist-info/RECORD
odoo9_addon_account_check_printing_report_dlt103-9.0.1.0.0.dist-info/metadata.json
odoo9_addon_account_check_printing_report_dlt103-9.0.1.0.0.dist-info/DESCRIPTION.rst
odoo9_addon_account_check_printing_report_dlt103-9.0.1.0.0.dist-info/METADATA
odoo9_addon_account_check_printing_report_dlt103-9.0.1.0.0.dist-info/namespace_packages.txt
odoo_addons/account_check_printing_report_dlt103/__openerp__.py
odoo_addons/account_check_printing_report_dlt103/__init__.py
odoo_addons/account_check_printing_report_dlt103/README.rst
odoo_addons/account_check_printing_report_dlt103/report/check_print.py
odoo_addons/account_check_printing_report_dlt103/report/account_check_writing_report.xml
odoo_addons/account_check_printing_report_dlt103/report/__init__.py
odoo_addons/account_check_printing_report_dlt103/views/report_check.xml
odoo_addons/account_check_printing_report_dlt103/data/account_payment_check_report_data.xml
odoo_addons/account_check_printing_report_dlt103/data/report_paperformat.xml
