Metadata-Version: 2.0
Name: odoo9-addon-account-check-printing-report-dlt103
Version: 9.0.1.0.0
Summary: Account Check Printing Report DLT103
Home-page: https://github.com/OCA/account-payment
Author: Eficent,Serpent Consulting Services Pvt. Ltd.,Odoo Community Association (OCA)
Author-email: support@odoo-community.org
License: AGPL-3
Platform: UNKNOWN
Requires-Dist: odoo (<9.1a,>=9.0a)
Requires-Dist: odoo9-addon-account-check-printing-report-base
Classifier: Programming Language :: Python :: 2.7
Classifier: Framework :: Odoo
Classifier: License :: OSI Approved :: GNU Affero General Public License v3
